Metadata-Version: 1.0
Name: vcfoot
Version: 1.1.3
Summary: vcfoot by Viniette & Clarity.
Home-page: UNKNOWN
Author: Shoya Yasuda @ Viniette & Clarity, Inc.
Author-email: selamatpagi1124@gmail.com
License: Required: Copyright notice in any social outputs.     Forbidden: Sublicense, Modifications, Distribution, Patent Grant, Use Trademark, Hold Liable.
Platform: UNKNOWN
